{
    "annotations": {
      "list": [
        {
          "builtIn": 1,
          "datasource": "-- Grafana --",
          "enable": true,
          "hide": true,
          "iconColor": "rgba(0, 211, 255, 1)",
          "limit": 100,
          "name": "Annotations & Alerts",
          "showIn": 0,
          "target": {
            "limit": 100,
            "matchAny": false,
            "tags": [],
            "type": "dashboard"
          },
          "type": "dashboard"
        }
      ]
    },
    "description": "",
    "editable": true,
    "fiscalYearStartMonth": 0,
    "gnetId": 9617,
    "graphTooltip": 1,
    "id": 8,
    "iteration": 1645822309302,
    "links": [],
    "liveNow": false,
    "panels": [
      {
        "alerting": {},
        "aliasColors": {
          "load 15m": "#CCA300",
          "load 1m": "#890F02",
          "load 5m": "#C15C17"
        },
        "bars": false,
        "dashLength": 10,
        "dashes": false,
        "editable": true,
        "error": false,
        "fill": 3,
        "fillGradient": 0,
        "grid": {},
        "gridPos": {
          "h": 4,
          "w": 3,
          "x": 0,
          "y": 0
        },
        "hiddenSeries": false,
        "id": 147,
        "legend": {
          "avg": false,
          "current": false,
          "max": false,
          "min": false,
          "show": false,
          "total": false,
          "values": false
        },
        "lines": true,
        "linewidth": 1,
        "links": [],
        "nullPointMode": "null",
        "options": {
          "alertThreshold": true
        },
        "percentage": false,
        "pluginVersion": "8.4.1",
        "pointradius": 5,
        "points": false,
        "renderer": "flot",
        "seriesOverrides": [],
        "spaceLength": 10,
        "stack": false,
        "steppedLine": false,
        "targets": [
          {
            "expr": "node_load1{host=\"$host\"}",
            "format": "time_series",
            "interval": "$step",
            "intervalFactor": 1,
            "legendFormat": "load 1m",
            "refId": "A",
            "step": 1200,
            "target": ""
          },
          {
            "expr": "node_load5{host=\"$host\"}",
            "format": "time_series",
            "interval": "$step",
            "intervalFactor": 1,
            "legendFormat": "load 5m",
            "refId": "B",
            "step": 1200,
            "target": ""
          },
          {
            "expr": "node_load15{host=\"$host\"}",
            "format": "time_series",
            "interval": "$step",
            "intervalFactor": 1,
            "legendFormat": "load 15m",
            "refId": "C",
            "step": 1200,
            "target": ""
          }
        ],
        "thresholds": [],
        "timeRegions": [],
        "title": "Load average",
        "tooltip": {
          "msResolution": false,
          "shared": true,
          "sort": 0,
          "value_type": "cumulative"
        },
        "type": "graph",
        "xaxis": {
          "mode": "time",
          "show": true,
          "values": []
        },
        "yaxes": [
          {
            "format": "short",
            "logBase": 1,
            "show": true
          },
          {
            "format": "short",
            "logBase": 1,
            "show": false
          }
        ],
        "yaxis": {
          "align": false
        }
      },
      {
        "fieldConfig": {
          "defaults": {
            "color": {
              "mode": "thresholds"
            },
            "mappings": [
              {
                "options": {
                  "match": "null",
                  "result": {
                    "text": "N/A"
                  }
                },
                "type": "special"
              }
            ],
            "thresholds": {
              "mode": "absolute",
              "steps": [
                {
                  "color": "rgba(245, 54, 54, 0.9)",
                  "value": null
                },
                {
                  "color": "rgba(237, 129, 40, 0.89)",
                  "value": 2
                },
                {
                  "color": "rgba(50, 172, 45, 0.97)",
                  "value": 4
                }
              ]
            },
            "unit": "none"
          },
          "overrides": []
        },
        "gridPos": {
          "h": 4,
          "w": 2,
          "x": 3,
          "y": 0
        },
        "id": 25,
        "links": [],
        "maxDataPoints": 100,
        "options": {
          "colorMode": "value",
          "graphMode": "area",
          "justifyMode": "auto",
          "orientation": "horizontal",
          "reduceOptions": {
            "calcs": [
              "lastNotNull"
            ],
            "fields": "",
            "values": false
          },
          "textMode": "auto"
        },
        "pluginVersion": "8.4.1",
        "targets": [
          {
            "expr": "scalar(count(count by (cpu)(node_cpu_seconds_total{host='$host'})))",
            "format": "time_series",
            "intervalFactor": 2,
            "legendFormat": "",
            "metric": "",
            "refId": "A",
            "step": 1800
          }
        ],
        "title": "CPU cores",
        "type": "stat"
      },
      {
        "fieldConfig": {
          "defaults": {
            "color": {
              "mode": "thresholds"
            },
            "decimals": 3,
            "mappings": [
              {
                "options": {
                  "match": "null",
                  "result": {
                    "text": "N/A"
                  }
                },
                "type": "special"
              }
            ],
            "max": 100,
            "min": 0,
            "thresholds": {
              "mode": "absolute",
              "steps": [
                {
                  "color": "rgba(50, 172, 45, 0.97)",
                  "value": null
                },
                {
                  "color": "rgba(237, 129, 40, 0.89)",
                  "value": 70
                },
                {
                  "color": "rgba(245, 54, 54, 0.9)",
                  "value": 95
                }
              ]
            },
            "unit": "short"
          },
          "overrides": []
        },
        "gridPos": {
          "h": 4,
          "w": 3,
          "x": 5,
          "y": 0
        },
        "id": 125,
        "links": [],
        "maxDataPoints": 100,
        "options": {
          "orientation": "horizontal",
          "reduceOptions": {
            "calcs": [
              "lastNotNull"
            ],
            "fields": "",
            "values": false
          },
          "showThresholdLabels": false,
          "showThresholdMarkers": true
        },
        "pluginVersion": "8.4.1",
        "targets": [
          {
            "expr": "(1 - avg(irate(node_cpu_seconds_total{host=\"$host\", mode='idle'}[$interval])))*100",
            "format": "time_series",
            "interval": "$step",
            "intervalFactor": 1,
            "legendFormat": "",
            "metric": "",
            "refId": "A",
            "step": 1800
          }
        ],
        "title": "Average cpu %",
        "type": "gauge"
      },
      {
        "fieldConfig": {
          "defaults": {
            "color": {
              "mode": "thresholds"
            },
            "decimals": 2,
            "mappings": [
              {
                "options": {
                  "match": "null",
                  "result": {
                    "text": "N/A"
                  }
                },
                "type": "special"
              }
            ],
            "thresholds": {
              "mode": "absolute",
              "steps": [
                {
                  "color": "dark-green",
                  "value": null
                },
                {
                  "color": "dark-red",
                  "value": 80
                }
              ]
            },
            "unit": "hertz"
          },
          "overrides": []
        },
        "gridPos": {
          "h": 2,
          "w": 2,
          "x": 8,
          "y": 0
        },
        "id": 79,
        "links": [],
        "maxDataPoints": 100,
        "options": {
          "colorMode": "none",
          "graphMode": "none",
          "justifyMode": "auto",
          "orientation": "horizontal",
          "reduceOptions": {
            "calcs": [
              "min"
            ],
            "fields": "",
            "values": false
          },
          "textMode": "auto"
        },
        "pluginVersion": "8.4.1",
        "targets": [
          {
            "expr": "min(node_cpu_frequency_min_hertz{host='$host'})",
            "format": "time_series",
            "intervalFactor": 2,
            "legendFormat": "",
            "metric": "",
            "refId": "A",
            "step": 1800
          }
        ],
        "title": "Min frequency",
        "type": "stat"
      },
      {
        "fieldConfig": {
          "defaults": {
            "color": {
              "mode": "thresholds"
            },
            "decimals": 2,
            "mappings": [
              {
                "options": {
                  "match": "null",
                  "result": {
                    "text": "N/A"
                  }
                },
                "type": "special"
              }
            ],
            "thresholds": {
              "mode": "absolute",
              "steps": [
                {
                  "color": "dark-green",
                  "value": null
                },
                {
                  "color": "dark-red",
                  "value": 80
                }
              ]
            },
            "unit": "hertz"
          },
          "overrides": []
        },
        "gridPos": {
          "h": 2,
          "w": 2,
          "x": 10,
          "y": 0
        },
        "id": 78,
        "links": [],
        "maxDataPoints": 100,
        "options": {
          "colorMode": "none",
          "graphMode": "none",
          "justifyMode": "auto",
          "orientation": "horizontal",
          "reduceOptions": {
            "calcs": [
              "max"
            ],
            "fields": "",
            "values": false
          },
          "textMode": "auto"
        },
        "pluginVersion": "8.4.1",
        "targets": [
          {
            "expr": "max(node_cpu_frequency_max_hertz{host='$host'})",
            "format": "time_series",
            "intervalFactor": 2,
            "legendFormat": "",
            "metric": "",
            "refId": "A",
            "step": 1800
          }
        ],
        "title": "Max frequency",
        "type": "stat"
      },
      {
        "fieldConfig": {
          "defaults": {
            "color": {
              "mode": "thresholds"
            },
            "decimals": 3,
            "mappings": [
              {
                "options": {
                  "match": "null",
                  "result": {
                    "text": "N/A"
                  }
                },
                "type": "special"
              }
            ],
            "max": 100,
            "min": 0,
            "thresholds": {
              "mode": "absolute",
              "steps": [
                {
                  "color": "rgba(50, 172, 45, 0.97)",
                  "value": null
                },
                {
                  "color": "rgba(237, 129, 40, 0.89)",
                  "value": 70
                },
                {
                  "color": "rgba(245, 54, 54, 0.9)",
                  "value": 95
                }
              ]
            },
            "unit": "short"
          },
          "overrides": []
        },
        "gridPos": {
          "h": 4,
          "w": 3,
          "x": 12,
          "y": 0
        },
        "id": 103,
        "links": [],
        "maxDataPoints": 100,
        "options": {
          "orientation": "horizontal",
          "reduceOptions": {
            "calcs": [
              "lastNotNull"
            ],
            "fields": "",
            "values": false
          },
          "showThresholdLabels": false,
          "showThresholdMarkers": true
        },
        "pluginVersion": "8.4.1",
        "targets": [
          {
            "expr": "100 * (avg(node_cpu_frequency_hertz{host='$host'})-min(node_cpu_frequency_min_hertz{host='$host'})) / (max(node_cpu_frequency_max_hertz{host='$host'})-min(node_cpu_frequency_min_hertz{host='$host'}))",
            "format": "time_series",
            "instant": false,
            "interval": "$step",
            "intervalFactor": 1,
            "legendFormat": "",
            "metric": "",
            "refId": "A",
            "step": 1800
          }
        ],
        "title": "Average frequency %",
        "type": "gauge"
      },
      {
        "fieldConfig": {
          "defaults": {
            "color": {
              "mode": "thresholds"
            },
            "decimals": 0,
            "mappings": [
              {
                "options": {
                  "0": {
                    "text": "OK"
                  }
                },
                "type": "value"
              },
              {
                "options": {
                  "match": "null",
                  "result": {
                    "text": "N/A"
                  }
                },
                "type": "special"
              }
            ],
            "max": 10,
            "min": 0,
            "thresholds": {
              "mode": "absolute",
              "steps": [
                {
                  "color": "rgba(50, 172, 45, 0.97)",
                  "value": null
                },
                {
                  "color": "rgba(237, 129, 40, 0.89)",
                  "value": 2
                },
                {
                  "color": "rgba(245, 54, 54, 0.9)",
                  "value": 3
                }
              ]
            },
            "unit": "short"
          },
          "overrides": []
        },
        "gridPos": {
          "h": 4,
          "w": 2,
          "x": 15,
          "y": 0
        },
        "id": 169,
        "links": [],
        "maxDataPoints": 100,
        "options": {
          "orientation": "horizontal",
          "reduceOptions": {
            "calcs": [
              "lastNotNull"
            ],
            "fields": "",
            "values": false
          },
          "showThresholdLabels": false,
          "showThresholdMarkers": true
        },
        "pluginVersion": "8.4.1",
        "targets": [
          {
            "expr": "sum(node_cpu_core_throttles_total{host='$host'})",
            "format": "time_series",
            "interval": "$step",
            "intervalFactor": 1,
            "legendFormat": "",
            "metric": "",
            "refId": "A",
            "step": 1800
          }
        ],
        "title": "Throttles core",
        "type": "gauge"
      },
      {
        "fieldConfig": {
          "defaults": {
            "color": {
              "mode": "thresholds"
            },
            "decimals": 0,
            "mappings": [
              {
                "options": {
                  "0": {
                    "text": "OK"
                  }
                },
                "type": "value"
              },
              {
                "options": {
                  "match": "null",
                  "result": {
                    "text": "N/A"
                  }
                },
                "type": "special"
              }
            ],
            "max": 10,
            "min": 0,
            "thresholds": {
              "mode": "absolute",
              "steps": [
                {
                  "color": "rgba(50, 172, 45, 0.97)",
                  "value": null
                },
                {
                  "color": "rgba(237, 129, 40, 0.89)",
                  "value": 2
                },
                {
                  "color": "rgba(245, 54, 54, 0.9)",
                  "value": 3
                }
              ]
            },
            "unit": "short"
          },
          "overrides": []
        },
        "gridPos": {
          "h": 4,
          "w": 2,
          "x": 17,
          "y": 0
        },
        "id": 191,
        "links": [],
        "maxDataPoints": 100,
        "options": {
          "orientation": "horizontal",
          "reduceOptions": {
            "calcs": [
              "lastNotNull"
            ],
            "fields": "",
            "values": false
          },
          "showThresholdLabels": false,
          "showThresholdMarkers": true
        },
        "pluginVersion": "8.4.1",
        "targets": [
          {
            "expr": "sum(node_cpu_package_throttles_total{host='$host'})",
            "format": "time_series",
            "interval": "$step",
            "intervalFactor": 1,
            "legendFormat": "",
            "metric": "",
            "refId": "A",
            "step": 1800
          }
        ],
        "title": "Throttles package",
        "type": "gauge"
      },
      {
        "alerting": {},
        "aliasColors": {
          "load 15m": "#CCA300",
          "load 1m": "#890F02",
          "load 5m": "#C15C17"
        },
        "bars": false,
        "dashLength": 10,
        "dashes": false,
        "editable": true,
        "error": false,
        "fill": 1,
        "fillGradient": 0,
        "grid": {},
        "gridPos": {
          "h": 4,
          "w": 5,
          "x": 19,
          "y": 0
        },
        "hiddenSeries": false,
        "id": 16,
        "legend": {
          "avg": false,
          "current": false,
          "max": false,
          "min": false,
          "show": false,
          "total": false,
          "values": false
        },
        "lines": true,
        "linewidth": 1,
        "links": [],
        "nullPointMode": "null",
        "options": {
          "alertThreshold": true
        },
        "percentage": false,
        "pluginVersion": "8.4.1",
        "pointradius": 5,
        "points": false,
        "renderer": "flot",
        "seriesOverrides": [],
        "spaceLength": 10,
        "stack": false,
        "steppedLine": false,
        "targets": [
          {
            "expr": "sum(irate(node_cpu_core_throttles_total{host=\"$host\"}[$interval]))",
            "format": "time_series",
            "interval": "$step",
            "intervalFactor": 1,
            "legendFormat": "Core",
            "refId": "A",
            "step": 1200,
            "target": ""
          },
          {
            "expr": "sum(irate(node_cpu_package_throttles_total{host=\"$host\"}[$interval]))",
            "format": "time_series",
            "interval": "$step",
            "intervalFactor": 1,
            "legendFormat": "Packages",
            "refId": "B",
            "step": 1200,
            "target": ""
          }
        ],
        "thresholds": [],
        "timeRegions": [],
        "title": "Throttles history",
        "tooltip": {
          "msResolution": false,
          "shared": true,
          "sort": 0,
          "value_type": "cumulative"
        },
        "type": "graph",
        "xaxis": {
          "mode": "time",
          "show": true,
          "values": []
        },
        "yaxes": [
          {
            "format": "short",
            "logBase": 1,
            "show": true
          },
          {
            "format": "short",
            "logBase": 1,
            "show": true
          }
        ],
        "yaxis": {
          "align": false
        }
      },
      {
        "fieldConfig": {
          "defaults": {
            "color": {
              "fixedColor": "rgba(126, 178, 109, 0)",
              "mode": "fixed"
            },
            "decimals": 2,
            "mappings": [
              {
                "options": {
                  "match": "null",
                  "result": {
                    "text": "N/A"
                  }
                },
                "type": "special"
              }
            ],
            "thresholds": {
              "mode": "absolute",
              "steps": [
                {
                  "color": "dark-green",
                  "value": null
                },
                {
                  "color": "dark-red",
                  "value": 80
                }
              ]
            },
            "unit": "hertz"
          },
          "overrides": []
        },
        "gridPos": {
          "h": 2,
          "w": 4,
          "x": 8,
          "y": 2
        },
        "id": 80,
        "links": [],
        "maxDataPoints": 100,
        "options": {
          "colorMode": "none",
          "graphMode": "area",
          "justifyMode": "auto",
          "orientation": "horizontal",
          "reduceOptions": {
            "calcs": [
              "mean"
            ],
            "fields": "",
            "values": false
          },
          "textMode": "auto"
        },
        "pluginVersion": "8.4.1",
        "targets": [
          {
            "expr": "avg(node_cpu_frequency_hertz{host='$host'})",
            "format": "time_series",
            "intervalFactor": 2,
            "legendFormat": "",
            "metric": "",
            "refId": "A",
            "step": 1800
          }
        ],
        "title": "Average frequency",
        "type": "stat"
      },
      {
        "collapsed": false,
        "gridPos": {
          "h": 1,
          "w": 24,
          "x": 0,
          "y": 4
        },
        "id": 55,
        "panels": [],
        "repeat": "cpu",
        "title": "CPU $cpu",
        "type": "row"
      },
      {
        "alerting": {},
        "aliasColors": {},
        "bars": false,
        "dashLength": 10,
        "dashes": false,
        "editable": true,
        "error": false,
        "fill": 5,
        "fillGradient": 0,
        "grid": {},
        "gridPos": {
          "h": 7,
          "w": 12,
          "x": 0,
          "y": 5
        },
        "hiddenSeries": false,
        "id": 3,
        "legend": {
          "avg": false,
          "current": false,
          "hideEmpty": false,
          "hideZero": false,
          "max": false,
          "min": false,
          "show": false,
          "total": false,
          "values": false
        },
        "lines": true,
        "linewidth": 0,
        "links": [],
        "maxPerRow": 4,
        "nullPointMode": "null",
        "options": {
          "alertThreshold": true
        },
        "percentage": false,
        "pluginVersion": "8.4.1",
        "pointradius": 5,
        "points": false,
        "renderer": "flot",
        "repeatDirection": "h",
        "seriesOverrides": [
          {
            "alias": "user",
            "color": "#629e51"
          },
          {
            "alias": "system",
            "color": "#bf1b00"
          },
          {
            "alias": "nice",
            "color": "#1f78c1"
          },
          {
            "alias": "irq",
            "color": "#511749"
          },
          {
            "alias": "softirq",
            "color": "#ba43a9"
          },
          {
            "alias": "steal",
            "color": "#99440a"
          },
          {
            "alias": "iowait",
            "color": "#f9934e"
          },
          {
            "alias": "idle",
            "color": "#052b51"
          }
        ],
        "spaceLength": 10,
        "stack": true,
        "steppedLine": false,
        "targets": [
          {
            "expr": "irate(node_cpu_seconds_total{host=\"$host\", mode='user', cpu='$cpu'}[$interval])",
            "format": "time_series",
            "hide": false,
            "instant": false,
            "interval": "$step",
            "intervalFactor": 1,
            "legendFormat": "{{ mode }}",
            "refId": "A",
            "step": 3000
          },
          {
            "expr": "irate(node_cpu_seconds_total{host=\"$host\", mode='system', cpu='$cpu'}[$interval])",
            "format": "time_series",
            "hide": false,
            "instant": false,
            "interval": "$step",
            "intervalFactor": 1,
            "legendFormat": "{{ mode }}",
            "refId": "B",
            "step": 3000
          },
          {
            "expr": "irate(node_cpu_seconds_total{host=\"$host\", mode='nice', cpu='$cpu'}[$interval])",
            "format": "time_series",
            "hide": false,
            "instant": false,
            "interval": "$step",
            "intervalFactor": 1,
            "legendFormat": "{{ mode }}",
            "refId": "C",
            "step": 3000
          },
          {
            "expr": "irate(node_cpu_seconds_total{host=\"$host\", mode='idle', cpu='$cpu'}[$interval])",
            "format": "time_series",
            "hide": false,
            "instant": false,
            "interval": "$step",
            "intervalFactor": 1,
            "legendFormat": "{{ mode }}",
            "refId": "H",
            "step": 3000
          },
          {
            "expr": "irate(node_cpu_seconds_total{host=\"$host\", mode='irq', cpu='$cpu'}[$interval])",
            "format": "time_series",
            "hide": false,
            "instant": false,
            "interval": "$step",
            "intervalFactor": 1,
            "legendFormat": "{{ mode }}",
            "refId": "D",
            "step": 3000
          },
          {
            "expr": "irate(node_cpu_seconds_total{host=\"$host\", mode='softirq', cpu='$cpu'}[$interval])",
            "format": "time_series",
            "hide": false,
            "instant": false,
            "interval": "$step",
            "intervalFactor": 1,
            "legendFormat": "{{ mode }}",
            "refId": "E",
            "step": 3000
          },
          {
            "expr": "irate(node_cpu_seconds_total{host=\"$host\", mode='iowait', cpu='$cpu'}[$interval])",
            "format": "time_series",
            "hide": false,
            "instant": false,
            "interval": "$step",
            "intervalFactor": 1,
            "legendFormat": "{{ mode }}",
            "refId": "F",
            "step": 3000
          },
          {
            "expr": "irate(node_cpu_seconds_total{host=\"$host\", mode='steal', cpu='$cpu'}[$interval])",
            "format": "time_series",
            "hide": false,
            "instant": false,
            "interval": "$step",
            "intervalFactor": 1,
            "legendFormat": "{{ mode }}",
            "refId": "G",
            "step": 3000
          }
        ],
        "thresholds": [],
        "timeRegions": [],
        "title": "Usage",
        "tooltip": {
          "msResolution": false,
          "shared": true,
          "sort": 0,
          "value_type": "individual"
        },
        "type": "graph",
        "xaxis": {
          "mode": "time",
          "show": true,
          "values": []
        },
        "yaxes": [
          {
            "format": "percentunit",
            "label": "",
            "logBase": 1,
            "max": "1",
            "min": "0",
            "show": true
          },
          {
            "format": "short",
            "logBase": 1,
            "show": false
          }
        ],
        "yaxis": {
          "align": false
        }
      },
      {
        "alerting": {},
        "aliasColors": {},
        "bars": false,
        "dashLength": 10,
        "dashes": false,
        "editable": true,
        "error": false,
        "fill": 0,
        "fillGradient": 0,
        "grid": {},
        "gridPos": {
          "h": 7,
          "w": 12,
          "x": 12,
          "y": 5
        },
        "hiddenSeries": false,
        "id": 56,
        "legend": {
          "avg": false,
          "current": false,
          "hideEmpty": false,
          "hideZero": false,
          "max": false,
          "min": false,
          "show": false,
          "total": false,
          "values": false
        },
        "lines": true,
        "linewidth": 1,
        "links": [],
        "maxPerRow": 4,
        "nullPointMode": "null",
        "options": {
          "alertThreshold": true
        },
        "percentage": false,
        "pluginVersion": "8.4.1",
        "pointradius": 5,
        "points": false,
        "renderer": "flot",
        "repeatDirection": "h",
        "seriesOverrides": [
          {
            "alias": "max",
            "color": "#bf1b00",
            "dashes": true
          },
          {
            "alias": "min",
            "color": "#7eb26d",
            "dashes": true
          },
          {
            "alias": "current",
            "color": "#f9934e",
            "lines": false,
            "pointradius": 1,
            "points": true
          }
        ],
        "spaceLength": 10,
        "stack": false,
        "steppedLine": false,
        "targets": [
          {
            "expr": "node_cpu_frequency_max_hertz{host='$host', cpu='$cpu'}",
            "format": "time_series",
            "interval": "$step",
            "intervalFactor": 1,
            "legendFormat": "max",
            "refId": "A"
          },
          {
            "expr": "node_cpu_frequency_hertz{host='$host', cpu='$cpu'}",
            "format": "time_series",
            "interval": "$step",
            "intervalFactor": 1,
            "legendFormat": "current",
            "refId": "B"
          },
          {
            "expr": "node_cpu_frequency_min_hertz{host='$host', cpu='$cpu'}",
            "format": "time_series",
            "interval": "$step",
            "intervalFactor": 1,
            "legendFormat": "min",
            "refId": "C"
          }
        ],
        "thresholds": [],
        "timeRegions": [],
        "title": "Frequency",
        "tooltip": {
          "msResolution": false,
          "shared": true,
          "sort": 0,
          "value_type": "cumulative"
        },
        "type": "graph",
        "xaxis": {
          "mode": "time",
          "show": true,
          "values": []
        },
        "yaxes": [
          {
            "format": "hertz",
            "label": "",
            "logBase": 1,
            "show": true
          },
          {
            "format": "short",
            "logBase": 1,
            "show": false
          }
        ],
        "yaxis": {
          "align": false
        }
      }
    ],
    "refresh": "5s",
    "schemaVersion": 35,
    "style": "dark",
    "tags": [
      "linux",
      "cpu",
      "provisioned"
    ],
    "templating": {
      "list": [
        {
          "current": {},
          "datasource": {
            "type": "prometheus",
            "uid": "P1809F7CD0C75ACF3"
          },
          "definition": "label_values(node_boot_time_seconds, host)",
          "error": {
            "config": {
              "data": {
                "end": "1645822320",
                "match[]": "node_boot_time_seconds",
                "start": "1645735920"
              },
              "headers": {
                "Content-Type": "application/x-www-form-urlencoded",
                "X-Grafana-Org-Id": 1
              },
              "hideFromInspector": true,
              "method": "POST",
              "retry": 0,
              "url": "api/datasources/proxy/13/api/v1/series"
            },
            "data": {
              "message": "Unable to find datasource"
            },
            "message": "Unable to find datasource",
            "status": 404,
            "statusText": "Not Found"
          },
          "hide": 0,
          "includeAll": false,
          "label": "",
          "multi": false,
          "name": "host",
          "options": [],
          "query": {
            "query": "label_values(node_boot_time_seconds, host)",
            "refId": "prometheus-host-Variable-Query"
          },
          "refresh": 2,
          "regex": "",
          "skipUrlSync": false,
          "sort": 1,
          "type": "query",
          "useTags": false
        },
        {
          "auto": false,
          "auto_count": 30,
          "auto_min": "10s",
          "current": {
            "selected": false,
            "text": "1m",
            "value": "1m"
          },
          "hide": 0,
          "label": "interval",
          "name": "interval",
          "options": [
            {
              "selected": false,
              "text": "30s",
              "value": "30s"
            },
            {
              "selected": true,
              "text": "1m",
              "value": "1m"
            },
            {
              "selected": false,
              "text": "5m",
              "value": "5m"
            },
            {
              "selected": false,
              "text": "10m",
              "value": "10m"
            },
            {
              "selected": false,
              "text": "1h",
              "value": "1h"
            },
            {
              "selected": false,
              "text": "6h",
              "value": "6h"
            },
            {
              "selected": false,
              "text": "12h",
              "value": "12h"
            }
          ],
          "query": "30s,1m,5m,10m,1h,6h,12h",
          "refresh": 2,
          "skipUrlSync": false,
          "type": "interval"
        },
        {
          "auto": false,
          "auto_count": 30,
          "auto_min": "10s",
          "current": {
            "selected": false,
            "text": "30s",
            "value": "30s"
          },
          "hide": 0,
          "label": "step",
          "name": "step",
          "options": [
            {
              "selected": true,
              "text": "30s",
              "value": "30s"
            },
            {
              "selected": false,
              "text": "1m",
              "value": "1m"
            },
            {
              "selected": false,
              "text": "5m",
              "value": "5m"
            },
            {
              "selected": false,
              "text": "10m",
              "value": "10m"
            },
            {
              "selected": false,
              "text": "1h",
              "value": "1h"
            },
            {
              "selected": false,
              "text": "6h",
              "value": "6h"
            },
            {
              "selected": false,
              "text": "12h",
              "value": "12h"
            }
          ],
          "query": "30s,1m,5m,10m,1h,6h,12h",
          "refresh": 2,
          "skipUrlSync": false,
          "type": "interval"
        },
        {
          "current": {},
          "datasource": {
            "type": "prometheus",
            "uid": "P1809F7CD0C75ACF3"
          },
          "definition": "label_values(node_cpu_seconds_total, cpu)",
          "error": {
            "config": {
              "data": {
                "end": "1645822320",
                "match[]": "node_cpu_seconds_total",
                "start": "1645735920"
              },
              "headers": {
                "Content-Type": "application/x-www-form-urlencoded",
                "X-Grafana-Org-Id": 1
              },
              "hideFromInspector": true,
              "method": "POST",
              "retry": 0,
              "url": "api/datasources/proxy/13/api/v1/series"
            },
            "data": {
              "message": "Unable to find datasource"
            },
            "message": "Unable to find datasource",
            "status": 404,
            "statusText": "Not Found"
          },
          "hide": 0,
          "includeAll": true,
          "label": "cpu",
          "multi": true,
          "name": "cpu",
          "options": [],
          "query": {
            "query": "label_values(node_cpu_seconds_total, cpu)",
            "refId": "prometheus-cpu-Variable-Query"
          },
          "refresh": 2,
          "regex": "",
          "skipUrlSync": false,
          "sort": 1,
          "tagValuesQuery": "",
          "tagsQuery": "",
          "type": "query",
          "useTags": false
        }
      ]
    },
    "time": {
      "from": "now-24h",
      "to": "now"
    },
    "timepicker": {
      "hidden": false,
      "refresh_intervals": [
        "5s",
        "10s",
        "30s",
        "1m",
        "5m",
        "15m",
        "30m",
        "1h",
        "2h",
        "1d"
      ],
      "time_options": [
        "5m",
        "15m",
        "1h",
        "6h",
        "12h",
        "24h",
        "2d",
        "7d",
        "30d"
      ]
    },
    "timezone": "browser",
    "title": "CPU",
    "uid": "j3RfFN8mk",
    "version": 3,
    "weekStart": ""
  }